nepthys/__init__.py
nepthys-0.0.0.dist-info/METADATA
nepthys-0.0.0.dist-info/RECORD
nepthys-0.0.0.dist-info/WHEEL
nepthys-0.0.0.dist-info/top_level.txt
