Metadata-Version: 2.1
Name: nepthys
Version: 0.0.0
Summary: Taking your code back to live as an interactive documentation automatically.
Home-page: UNKNOWN
Author: Fridolin Pokorny
Author-email: fridolin@redhat.com
License: GPLv3+
Platform: UNKNOWN
